counter_design/counter_design.v
/* Specifications:
    - 4 bit up-counter
    - Active high, synchronous reset
    - Active high enable
*/

module counter (
    clock,
    reset, // active high, synchronous reset INPUT
    enable, // active high enable
    counter_out // 4-bit vector output
);

input clock;
input reset;
input enable;
output [3:0] counter_output;

wire clock;
wire reset;
wire enable;
reg [3:0] counter_out;

always @ (posedge clock)
begin: counter
    // Check if RESET is active at every rising clock edge
    // If RESET is active, counter outputs 4'b0000 (4-bit number 0000)
    if (reset == 1'b1) begin
        counter_out <= #1 4'b0000;
        // <= is non-blocking, used in sequential logic, and occurs in parallel
        // = is blocking, used in combinational logic, and occurs sequentially
    end

    // If ENABLE is active, increment the counter
    else if (enable == 1'b1) begin
        counter_out <= #1 counter_out + 1
    end
end
endmodule

counter_design/counter_design_tb.v
module counter_design_tb();

// Declare inputs as regs & outputs as wires
reg clock, reset, enable;
wire [3:0] counter_out;

// Initialize variables
initial begin
    $display ("Time\t Clock\t Reset\t Enable\t Counter\t");
    $monitor ("%g\t %b\t %b\t %b\t %b\t",
              $time, clock, reset, enable, counter_out);
    clock = 1;
    reset = 0;
    enable = 0;
    #5 reset = 1;
    #10 reset = 0;
    #10 enable = 1;
    #100 enable = 0;
    #5 $finish;
end

// Clock Generator
always begin
    #5 clock = ~clock; // toggle clock every 5 time units
end

// Connect DUT to test bench
counter U_counter (
    clock,
    reset,
    enable,
    counter_out
);
endmodule

counter_design/counter_design_tb.vcd
$date
	Sat May 22 17:35:03 2021
$end
$version
	Icarus Verilog
$end
$timescale
	1s
$end
$scope module counter_design_tb $end
$var wire 4 ! counter_out [3:0] $end
$var reg 1 " clock $end
$var reg 1 # enable $end
$var reg 1 $ reset $end
$scope module U_counter $end
$var wire 1 " clock $end
$var wire 1 # enable $end
$var wire 1 $ reset $end
$var reg 4 % counter_out [3:0] $end
$scope begin counter $end
$upscope $end
$upscope $end
$upscope $end
$enddefinitions $end
#0
$dumpvars
bx %
0$
0#
1"
bx !
$end
#5
0"
1$
#10
1"
#11
b0 !
b0 %
#15
0"
0$
#20
1"
#25
0"
1#
#30
1"
#31
b1 !
b1 %
#35
0"
#40
1"
#41
b10 !
b10 %
#45
0"
#50
1"
#51
b11 !
b11 %
#55
0"
#60
1"
#61
b100 !
b100 %
#65
0"
#70
1"
#71
b101 !
b101 %
#75
0"
#80
1"
#81
b110 !
b110 %
#85
0"
#90
1"
#91
b111 !
b111 %
#95
0"
#100
1"
#101
b1000 !
b1000 %
#105
0"
#110
1"
#111
b1001 !
b1001 %
#115
0"
#120
1"
#121
b1010 !
b1010 %
#125
0"
0#
